graphviz_py/cli.py
graphviz_py/graphviz.py
graphviz_py/parser.py
graphviz_py/project.py
graphviz_py-1.0.8.dist-info/entry_points.txt
graphviz_py-1.0.8.dist-info/LICENSE
graphviz_py-1.0.8.dist-info/WHEEL
graphviz_py-1.0.8.dist-info/METADATA
graphviz_py-1.0.8.dist-info/RECORD
