Metadata-Version: 2.1
Name: graphviz-py
Version: 1.0.8
Summary: Allows Python code execution inside of graphviz diagrams.
Home-page: https://github.com/Alwinator/graphviz-py
License: MPL-2.0
Keywords: graphviz,dot,python,graphviz-python,gv
Author: Alwin Schuster
Author-email: contact@alwinschuster.at
Requires-Python: >=3.8.0
Classifier: License :: OSI Approved
Classifier: Programming Language :: Python :: 3
Classifier: Programming Language :: Python :: 3.10
Classifier: Programming Language :: Python :: 3.8
Classifier: Programming Language :: Python :: 3.9
Project-URL: Documentation, https://github.com/Alwinator/graphviz-py
Project-URL: Repository, https://github.com/Alwinator/graphviz-py
